latex_generator/__init__.py
latex_generator/latex_generator.py
latex_generator_lilyreber-0.2.dist-info/METADATA
latex_generator_lilyreber-0.2.dist-info/WHEEL
latex_generator_lilyreber-0.2.dist-info/top_level.txt
latex_generator_lilyreber-0.2.dist-info/RECORD
