Metadata-Version: 2.2
Name: latex_generator_lilyreber
Version: 0.2
Summary: A library for generating LaTeX code.
Author-email: Liliia Imamutdinova <lilyreber404@gmail.com>
Requires-Python: >=3.10
